{"responses":{"200":{"description":"OK","content":{"application/json":{"schema":{"allOf":[{"type":"object","properties":{"data":{},"error":{"type":"object","properties":{"code":{"type":"string"},"details":{"type":"string"},"message":{"type":"string"}}},"meta":{"type":"object","properties":{"count":{"type":"integer"},"limit":{"type":"integer"},"offset":{"type":"integer"},"total":{"type":"integer"}}},"success":{"type":"boolean"}}},{"type":"object","properties":{"data":{"type":"object","properties":{"available_segments":{"type":"integer"},"created_at":{"type":"string"},"encryption":{"type":"string"},"file_size":{"type":"integer"},"modified_at":{"type":"string"},"nested_sources":{"type":"array","items":{"type":"object","properties":{"encrypted":{"type":"boolean"},"inner_length":{"type":"integer"},"inner_volume_size":{"type":"integer"},"segment_count":{"type":"integer"},"segments":{"type":"array","items":{"type":"object","properties":{"end_offset":{"type":"integer"},"message_id":{"type":"string"},"segment_size":{"type":"integer"},"start_offset":{"type":"integer"}}}},"volume_index":{"type":"integer"}}}},"password_protected":{"type":"boolean"},"segment_count":{"type":"integer"},"segments":{"type":"array","items":{"type":"object","properties":{"available":{"type":"boolean"},"end_offset":{"type":"integer"},"message_id":{"type":"string"},"segment_size":{"type":"integer"},"start_offset":{"type":"integer"}}}},"source_nzb_path":{"type":"string"},"status":{"type":"string"}}}}}]}}}},"400":{"description":"Bad Request","content":{"application/json":{"schema":{"type":"object","properties":{"data":{},"error":{"type":"object","properties":{"code":{"type":"string"},"details":{"type":"string"},"message":{"type":"string"}}},"meta":{"type":"object","properties":{"count":{"type":"integer"},"limit":{"type":"integer"},"offset":{"type":"integer"},"total":{"type":"integer"}}},"success":{"type":"boolean"}}}}}},"404":{"description":"Not Found","content":{"application/json":{"schema":{"type":"object","properties":{"data":{},"error":{"type":"object","properties":{"code":{"type":"string"},"details":{"type":"string"},"message":{"type":"string"}}},"meta":{"type":"object","properties":{"count":{"type":"integer"},"limit":{"type":"integer"},"offset":{"type":"integer"},"total":{"type":"integer"}}},"success":{"type":"boolean"}}}}}},"500":{"description":"Internal Server Error","content":{"application/json":{"schema":{"type":"object","properties":{"data":{},"error":{"type":"object","properties":{"code":{"type":"string"},"details":{"type":"string"},"message":{"type":"string"}}},"meta":{"type":"object","properties":{"count":{"type":"integer"},"limit":{"type":"integer"},"offset":{"type":"integer"},"total":{"type":"integer"}}},"success":{"type":"boolean"}}}}}}}}